gcpmetrics
