Metadata-Version: 1.0
Name: gcpmetrics
Version: 1.0.35
Summary: Google Cloud Monitoring API Command Line
Home-page: https://github.com/odin-public/gcpmetrics
Author: Odin - Ingram Micro Company
Author-email: aps@odin.com
License: BSD
Platform: UNKNOWN
